myCalc9/__init__.py
myCalc9/arithmetics.py
myCalc9-0.0.1.dist-info/METADATA
myCalc9-0.0.1.dist-info/WHEEL
myCalc9-0.0.1.dist-info/top_level.txt
myCalc9-0.0.1.dist-info/RECORD
