Metadata-Version: 2.1
Name: myCalc9
Version: 0.0.1
Summary: A small mathematical library for quick calculations
Home-page: UNKNOWN
Author: Divyanshu Singh
Author-email: divyanshu.singh144400@gmail.com
License: MIT
Platform: UNKNOWN
Classifier: License :: OSI Approved :: MIT License
Classifier: Programming Language :: Python :: 3
Classifier: Operating System :: OS Independent
Requires-Python: >=3.6
